django_scheduled_tasks/__init__.py
django_scheduled_tasks/admin.py
django_scheduled_tasks/apps.py
django_scheduled_tasks/base.py
django_scheduled_tasks/management/__init__.py
django_scheduled_tasks/management/commands/__init__.py
django_scheduled_tasks/management/commands/run_task_scheduler.py
django_scheduled_tasks/migrations/0001_initial.py
django_scheduled_tasks/migrations/0002_scheduledtaskrunlog_last_scheduled_run_time_and_more.py
django_scheduled_tasks/migrations/0003_alter_scheduledtaskrunlog_options_and_more.py
django_scheduled_tasks/migrations/__init__.py
django_scheduled_tasks/models.py
django_scheduled_tasks-0.2.17.dist-info/WHEEL
django_scheduled_tasks-0.2.17.dist-info/METADATA
django_scheduled_tasks-0.2.17.dist-info/RECORD
