Metadata-Version: 2.3
Name: django-scheduled-tasks
Version: 0.2.17
Summary: Task scheduling for Django 6.0 task backends
Author: Lode Braced
Author-email: Lode Braced <lode@braced.dev>
Classifier: Development Status :: 4 - Beta
Classifier: License :: OSI Approved :: MIT License
Classifier: Intended Audience :: Developers
Classifier: Operating System :: OS Independent
Classifier: Programming Language :: Python
Classifier: Topic :: Software Development :: Libraries :: Python Modules
Classifier: Typing :: Typed
Classifier: Framework :: Django
Classifier: Framework :: Django :: 6.0
Requires-Dist: cron-converter>=1.3.1
Requires-Dist: django>=6.0
Requires-Dist: django-tasks>=0.10.0
Requires-Dist: pydantic>=2.12.5
Requires-Dist: pydantic-extra-types[cron]>=2.10.6
Requires-Python: >=3.12
Project-URL: Repository, https://github.com/lode-braced/django-scheduled-tasks
